eccodes/__init__.py
eccodes/__main__.py
eccodes/eccodes.py
eccodes/highlevel/__init__.py
eccodes/highlevel/message.py
eccodes/highlevel/reader.py
eccodes/highlevel/_bufr/BUFR_Snippets.md
eccodes/highlevel/_bufr/BUFR_Tour.md
eccodes/highlevel/_bufr/__init__.py
eccodes/highlevel/_bufr/coder.py
eccodes/highlevel/_bufr/common.py
eccodes/highlevel/_bufr/data.py
eccodes/highlevel/_bufr/header.py
eccodes/highlevel/_bufr/helpers.py
eccodes/highlevel/_bufr/message.py
eccodes/highlevel/_bufr/tables.py
eccodes/highlevel/_bufr/tree.py
eccodes/highlevel/_bufr/view.py
eccodes-2.45.0.dist-info/licenses/LICENSE
gribapi/__init__.py
gribapi/bindings.py
gribapi/eccodes.h
gribapi/errors.py
gribapi/grib_api.h
gribapi/gribapi.py
eccodes-2.45.0.dist-info/METADATA
eccodes-2.45.0.dist-info/WHEEL
eccodes-2.45.0.dist-info/top_level.txt
eccodes-2.45.0.dist-info/zip-safe
eccodes-2.45.0.dist-info/RECORD
