Metadata-Version: 2.1
Name: eccodes
Version: 2.45.0
Summary: Python interface to the ecCodes GRIB and BUFR decoder/encoder
Home-page: https://github.com/ecmwf/eccodes-python
Author: European Centre for Medium-Range Weather Forecasts (ECMWF)
Author-email: software.support@ecmwf.int
License: Apache License Version 2.0
Keywords: ecCodes GRIB BUFR
Classifier: Development Status :: 4 - Beta
Classifier: Intended Audience :: Developers
Classifier: License :: OSI Approved :: Apache Software License
Classifier: Programming Language :: Python :: 3.9
Classifier: Programming Language :: Python :: 3.10
Classifier: Programming Language :: Python :: 3.11
Classifier: Programming Language :: Python :: 3.12
Classifier: Programming Language :: Python :: 3.13
Classifier: Programming Language :: Python :: Implementation :: CPython
Classifier: Programming Language :: Python :: Implementation :: PyPy
Classifier: Operating System :: OS Independent
License-File: LICENSE
Requires-Dist: numpy
Requires-Dist: attrs
Requires-Dist: cffi
Requires-Dist: findlibs
